generator/__init__.py
generator/footer.py
generator/group.py
generator/marker.py
generator/milestone.py
generator/painter.py
generator/roadmap.py
generator/task.py
generator/timeline.py
generator/timelineitem.py
generator/timelinemode.py
generator/title.py
roadmap_generator-0.1.0b2.dist-info/LICENSE.md
roadmap_generator-0.1.0b2.dist-info/METADATA
roadmap_generator-0.1.0b2.dist-info/WHEEL
roadmap_generator-0.1.0b2.dist-info/top_level.txt
roadmap_generator-0.1.0b2.dist-info/RECORD
