Metadata-Version: 2.1
Name: roadmap-generator
Version: 0.1.0b2
Summary: Roadmap Generator. A Roadmap-as-Code (RaC) tool for generating a roadmap by using python code
Author-email: cs.goh@outlook.com
Classifier: Programming Language :: Python :: 3
Classifier: License :: OSI Approved :: MIT License
Classifier: Operating System :: OS Independent
License-File: LICENSE.md
Requires-Dist: pycairo (>=1.21.0)
Requires-Dist: colour (>=0.1.5)
Requires-Dist: python-dateutil (>=2.8.2)
